combot_installer/__init__.py
combot_installer/installer.py
combot_installer-0.1.0.dist-info/METADATA
combot_installer-0.1.0.dist-info/WHEEL
combot_installer-0.1.0.dist-info/top_level.txt
combot_installer-0.1.0.dist-info/RECORD
