Metadata-Version: 2.1
Name: combot_installer
Version: 0.1.0
Summary: A tool for automated installation
Author: Hkcode
Author-email: sissokoadel057@gmail.com
Classifier: Programming Language :: Python :: 3
Classifier: Programming Language :: Python :: 3.12
Classifier: License :: OSI Approved :: MIT License
